[{"students": [{"total": 24, "name": "\u738b\u98de", "faculty": "\u8f7b\u5de5\u5316\u5de5\u5b66\u9662"}, {"total": 24, "name": "\u6881\u4f1f\u840d", "faculty": "\u8f7b\u5de5\u5316\u5de5\u5b66\u9662"}, {"total": 23, "name": "\u9ec4\u8273\u73b2", "faculty": "\u8f7b\u5de5\u5316\u5de5\u5b66\u9662"}, {"total": 22, "name": "\u8521\u6587\u751f", "faculty": "\u8f7b\u5de5\u5316\u5de5\u5b66\u9662"}, {"total": 22, "name": "\u674e\u6865\u4f73", "faculty": "\u8f7b\u5de5\u5316\u5de5\u5b66\u9662"}, {"total": 22, "name": "\u674e\u946b\u5269", "faculty": "\u8f7b\u5de5\u5316\u5de5\u5b66\u9662"}, {"total": 22, "name": "\u90d1\u534e\u94a6", "faculty": "\u8f7b\u5de5\u5316\u5de5\u5b66\u9662"}, {"total": 22, "name": "\u909d\u51e4\u82ac", "faculty": "\u8f7b\u5de5\u5316\u5de5\u5b66\u9662"}, {"total": 21, "name": "\u674e\u8fbe\u660e", "faculty": "\u8f7b\u5de5\u5316\u5de5\u5b66\u9662"}, {"total": 21, "name": "\u5ed6\u5bb6\u6d77", "faculty": "\u8f7b\u5de5\u5316\u5de5\u5b66\u9662"}, {"total": 20, "name": "\u9648\u96c5\u96c4", "faculty": "\u8f7b\u5de5\u5316\u5de5\u5b66\u9662"}, {"total": 20, "name": "\u5085\u6c38\u4e3d", "faculty": "\u8f7b\u5de5\u5316\u5de5\u5b66\u9662"}, {"total": 20, "name": "\u5b81\u5c11\u519b", "faculty": "\u8f7b\u5de5\u5316\u5de5\u5b66\u9662"}, {"total": 20, "name": "\u738b\u6d77\u66fc", "faculty": "\u8f7b\u5de5\u5316\u5de5\u5b66\u9662"}], "total": 5, "name": "\u8f7b\u5de5\u5316\u5de5\u5b66\u9662"}, {"students": [], "total": 24, "name": "\u91d1\u5de5\u5b9e\u4e60\u4e2d\u5fc3"}, {"students": [], "total": 4, "name": "\u4f53\u80b2\u90e8"}, {"students": [], "total": 99, "name": "\u7ee7\u7eed\u6559\u80b2\u5b66\u9662"}, {"students": [], "total": 4, "name": "\u5e94\u7528\u6570\u5b66\u5b66\u9662"}, {"students": [], "total": 25, "name": "\u5927\u5b66\u5916\u8bed\u90e8"}, {"students": [], "total": 37, "name": "\u79bb\u9000\u529e"}, {"students": [{"total": 34, "name": "\u4f59\u5efa\u82f1", "faculty": "\u7ecf\u6d4e\u7ba1\u7406\u5b66\u9662"}, {"total": 31, "name": "\u9648\u5317\u5143", "faculty": "\u7ecf\u6d4e\u7ba1\u7406\u5b66\u9662"}, {"total": 30, "name": "\u9648\u6cfd\u6df1", "faculty": "\u7ecf\u6d4e\u7ba1\u7406\u5b66\u9662"}, {"total": 27, "name": "\u674e\u51e4", "faculty": "\u7ecf\u6d4e\u7ba1\u7406\u5b66\u9662"}, {"total": 27, "name": "\u9ec4\u78a7\u5bb9", "faculty": "\u7ecf\u6d4e\u7ba1\u7406\u5b66\u9662"}, {"total": 27, "name": "\u4f58\u7f8e\u82b8", "faculty": "\u7ecf\u6d4e\u7ba1\u7406\u5b66\u9662"}, {"total": 26, "name": "\u738b\u8f89\u535a", "faculty": "\u7ecf\u6d4e\u7ba1\u7406\u5b66\u9662"}, {"total": 25, "name": "\u8bb8\u5c11\u8679", "faculty": "\u7ecf\u6d4e\u7ba1\u7406\u5b66\u9662"}, {"total": 24, "name": "\u5434\u9526\u6cd3", "faculty": "\u7ecf\u6d4e\u7ba1\u7406\u5b66\u9662"}, {"total": 23, "name": "\u5218\u8273\u660e", "faculty": "\u7ecf\u6d4e\u7ba1\u7406\u5b66\u9662"}, {"total": 23, "name": "\u66fe\u7acb\u6885", "faculty": "\u7ecf\u6d4e\u7ba1\u7406\u5b66\u9662"}, {"total": 22, "name": "\u9648\u6587\u5349", "faculty": "\u7ecf\u6d4e\u7ba1\u7406\u5b66\u9662"}, {"total": 22, "name": "\u5218\u7d20\u5e73", "faculty": "\u7ecf\u6d4e\u7ba1\u7406\u5b66\u9662"}, {"total": 22, "name": "\u738b\u4e3d\u52e4", "faculty": "\u7ecf\u6d4e\u7ba1\u7406\u5b66\u9662"}, {"total": 22, "name": "\u66fe\u8fdc\u5170", "faculty": "\u7ecf\u6d4e\u7ba1\u7406\u5b66\u9662"}, {"total": 22, "name": "\u949f\u590f\u9752", "faculty": "\u7ecf\u6d4e\u7ba1\u7406\u5b66\u9662"}, {"total": 21, "name": "\u9648\u5de7\u513f", "faculty": "\u7ecf\u6d4e\u7ba1\u7406\u5b66\u9662"}, {"total": 21, "name": "\u9648\u5a49\u5a25", "faculty": "\u7ecf\u6d4e\u7ba1\u7406\u5b66\u9662"}, {"total": 21, "name": "\u51af\u7fa4\u5e86", "faculty": "\u7ecf\u6d4e\u7ba1\u7406\u5b66\u9662"}, {"total": 21, "name": "\u5f20\u82b3\u96ea", "faculty": "\u7ecf\u6d4e\u7ba1\u7406\u5b66\u9662"}, {"total": 21, "name": "\u5468\u745e\u5a1f", "faculty": "\u7ecf\u6d4e\u7ba1\u7406\u5b66\u9662"}, {"total": 21, "name": "\u5468\u6cf3\u5b8f", "faculty": "\u7ecf\u6d4e\u7ba1\u7406\u5b66\u9662"}, {"total": 21, "name": "\u5353\u6653\u971e", "faculty": "\u7ecf\u6d4e\u7ba1\u7406\u5b66\u9662"}, {"total": 21, "name": "\u8983\u96ea\u8273", "faculty": "\u7ecf\u6d4e\u7ba1\u7406\u5b66\u9662"}, {"total": 20, "name": "\u660c\u6167", "faculty": "\u7ecf\u6d4e\u7ba1\u7406\u5b66\u9662"}, {"total": 20, "name": "\u9ec4\u745c", "faculty": "\u7ecf\u6d4e\u7ba1\u7406\u5b66\u9662"}, {"total": 20, "name": "\u6797\u82b7\u51b0", "faculty": "\u7ecf\u6d4e\u7ba1\u7406\u5b66\u9662"}, {"total": 20, "name": "\u5218\u4e3d\u4e3d", "faculty": "\u7ecf\u6d4e\u7ba1\u7406\u5b66\u9662"}, {"total": 20, "name": "\u7f57\u5b66\u5f3a", "faculty": "\u7ecf\u6d4e\u7ba1\u7406\u5b66\u9662"}, {"total": 20, "name": "\u6c88\u5c1a\u950b", "faculty": "\u7ecf\u6d4e\u7ba1\u7406\u5b66\u9662"}, {"total": 20, "name": "\u8c22\u667a\u806a", "faculty": "\u7ecf\u6d4e\u7ba1\u7406\u5b66\u9662"}, {"total": 20, "name": "\u4f59\u5c0f\u971e", "faculty": "\u7ecf\u6d4e\u7ba1\u7406\u5b66\u9662"}, {"total": 20, "name": "\u66fe\u6842\u5a1f", "faculty": "\u7ecf\u6d4e\u7ba1\u7406\u5b66\u9662"}, {"total": 19, "name": "\u4e18\u60e0", "faculty": "\u7ecf\u6d4e\u7ba1\u7406\u5b66\u9662"}], "total": 25611, "name": "\u7ecf\u6d4e\u7ba1\u7406\u5b66\u9662"}, {"students": [], "total": 10, "name": "\u8ba1\u7b97\u4e2d\u5fc3"}, {"students": [{"total": 24, "name": "\u9ec4\u4e39", "faculty": "\u5e94\u7528\u7269\u7406\u7cfb"}, {"total": 20, "name": "\u5218\u5e7f\u624d", "faculty": "\u5e94\u7528\u7269\u7406\u7cfb"}, {"total": 19, "name": "\u4e01\u8bd7\u901a", "faculty": "\u5e94\u7528\u7269\u7406\u7cfb"}, {"total": 19, "name": "\u5362\u6587\u6ed4", "faculty": "\u5e94\u7528\u7269\u7406\u7cfb"}], "total": 3746, "name": "\u5e94\u7528\u7269\u7406\u7cfb"}, {"students": [], "total": 34, "name": "\u5b9e\u9a8c\u7814\u7a76\u4e2d\u5fc3"}, {"students": [{"total": 24, "name": "\u533a\u6dd1\u7ea2", "faculty": "\u73af\u5883\u5de5\u7a0b\u5b66\u9662"}, {"total": 23, "name": "\u5ed6\u519b\u624d", "faculty": "\u73af\u5883\u5de5\u7a0b\u5b66\u9662"}, {"total": 21, "name": "\u6c5f\u79c0\u82b1", "faculty": "\u73af\u5883\u5de5\u7a0b\u5b66\u9662"}, {"total": 20, "name": "\u5f90\u63a5\u80dc", "faculty": "\u73af\u5883\u5de5\u7a0b\u5b66\u9662"}], "total": 4547, "name": "\u73af\u5883\u5de5\u7a0b\u5b66\u9662"}, {"students": [], "total": 7, "name": "\u5efa\u7b51\u5b66\u4e13\u4e1a"}, {"students": [], "total": 3, "name": "\u6587\u5316\u7d20\u8d28\u6559\u80b2\u4e2d\u5fc3"}, {"students": [{"total": 30, "name": "\u8c2d\u5efa\u658c", "faculty": "\u4fe1\u606f\u5de5\u7a0b\u5b66\u9662"}, {"total": 30, "name": "\u5f20\u6cfd\u52c7", "faculty": "\u4fe1\u606f\u5de5\u7a0b\u5b66\u9662"}, {"total": 28, "name": "\u9648\u7fbd\u65fb", "faculty": "\u4fe1\u606f\u5de5\u7a0b\u5b66\u9662"}, {"total": 26, "name": "\u5468\u70b3\u836b", "faculty": "\u4fe1\u606f\u5de5\u7a0b\u5b66\u9662"}, {"total": 24, "name": "\u82cf\u9526\u6d2a", "faculty": "\u4fe1\u606f\u5de5\u7a0b\u5b66\u9662"}, {"total": 22, "name": "\u5f20\u6d77\u658c", "faculty": "\u4fe1\u606f\u5de5\u7a0b\u5b66\u9662"}, {"total": 21, "name": "\u8d75\u632f\u5764", "faculty": "\u4fe1\u606f\u5de5\u7a0b\u5b66\u9662"}, {"total": 20, "name": "\u6556\u6e5b\u658c", "faculty": "\u4fe1\u606f\u5de5\u7a0b\u5b66\u9662"}, {"total": 20, "name": "\u9ea6\u7ee7\u8363", "faculty": "\u4fe1\u606f\u5de5\u7a0b\u5b66\u9662"}, {"total": 19, "name": "\u9ec4\u9896", "faculty": "\u4fe1\u606f\u5de5\u7a0b\u5b66\u9662"}], "total": 6, "name": "\u4fe1\u606f\u5de5\u7a0b\u5b66\u9662"}, {"students": [], "total": 20, "name": "\u5316\u5b66\u5de5\u7a0b\u4e0e\u5de5\u827a\u4e13\u4e1a"}, {"students": [{"total": 32, "name": "\u674e\u7d20\u82b1", "faculty": "\u5efa\u8bbe\u5b66\u9662"}, {"total": 27, "name": "\u674e\u666f\u950b", "faculty": "\u5efa\u8bbe\u5b66\u9662"}, {"total": 21, "name": "\u5218\u7fe0\u6587", "faculty": "\u5efa\u8bbe\u5b66\u9662"}, {"total": 19, "name": "\u9ec4\u7acb\u94a7", "faculty": "\u5efa\u8bbe\u5b66\u9662"}, {"total": 19, "name": "\u9ec4\u52c7\u8f89", "faculty": "\u5efa\u8bbe\u5b66\u9662"}], "total": 10918, "name": "\u5efa\u8bbe\u5b66\u9662"}, {"students": [], "total": 15, "name": "\u8ba1\u7b97\u673a\u79d1\u5b66\u4e13\u4e1a"}, {"students": [{"total": 36, "name": "\u9a6c\u6da6\u8f89", "faculty": "\u81ea\u52a8\u5316\u5b66\u9662"}, {"total": 33, "name": "\u5f20\u4e3d\u5a1c", "faculty": "\u81ea\u52a8\u5316\u5b66\u9662"}, {"total": 28, "name": "\u9648\u8457\u660e", "faculty": "\u81ea\u52a8\u5316\u5b66\u9662"}, {"total": 26, "name": "\u5f20\u806a\u6167", "faculty": "\u81ea\u52a8\u5316\u5b66\u9662"}, {"total": 25, "name": "\u4e18\u4ed9\u5175", "faculty": "\u81ea\u52a8\u5316\u5b66\u9662"}, {"total": 24, "name": "\u8346\u6000\u6210", "faculty": "\u81ea\u52a8\u5316\u5b66\u9662"}, {"total": 24, "name": "\u82cf\u7956\u624d", "faculty": "\u81ea\u52a8\u5316\u5b66\u9662"}, {"total": 23, "name": "\u6768\u660e\u7136", "faculty": "\u81ea\u52a8\u5316\u5b66\u9662"}, {"total": 23, "name": "\u5468\u6b66\u6770", "faculty": "\u81ea\u52a8\u5316\u5b66\u9662"}, {"total": 23, "name": "\u6731\u6653\u950b", "faculty": "\u81ea\u52a8\u5316\u5b66\u9662"}, {"total": 22, "name": "\u674e\u4f1f", "faculty": "\u81ea\u52a8\u5316\u5b66\u9662"}, {"total": 22, "name": "\u674e\u4f1f\u9752", "faculty": "\u81ea\u52a8\u5316\u5b66\u9662"}, {"total": 22, "name": "\u8bb8\u51ef\u65b0", "faculty": "\u81ea\u52a8\u5316\u5b66\u9662"}, {"total": 21, "name": "\u50a8\u7075\u65bd", "faculty": "\u81ea\u52a8\u5316\u5b66\u9662"}, {"total": 21, "name": "\u5f20  \u7acb", "faculty": "\u81ea\u52a8\u5316\u5b66\u9662"}, {"total": 20, "name": "\u82cf\u8d32", "faculty": "\u81ea\u52a8\u5316\u5b66\u9662"}, {"total": 20, "name": "\u9648\u6653\u9f99", "faculty": "\u81ea\u52a8\u5316\u5b66\u9662"}, {"total": 20, "name": "\u6797\u5b97\u53f6", "faculty": "\u81ea\u52a8\u5316\u5b66\u9662"}, {"total": 20, "name": "\u5434\u674e\u6797", "faculty": "\u81ea\u52a8\u5316\u5b66\u9662"}, {"total": 20, "name": "\u5f20\u84dd\u5929", "faculty": "\u81ea\u52a8\u5316\u5b66\u9662"}, {"total": 20, "name": "\u6731\u4f1f\u8881", "faculty": "\u81ea\u52a8\u5316\u5b66\u9662"}, {"total": 19, "name": "\u9648\u4f1f", "faculty": "\u81ea\u52a8\u5316\u5b66\u9662"}, {"total": 19, "name": "\u5218\u6cbb", "faculty": "\u81ea\u52a8\u5316\u5b66\u9662"}, {"total": 19, "name": "\u9ec4\u4e3d\u82f1", "faculty": "\u81ea\u52a8\u5316\u5b66\u9662"}, {"total": 19, "name": "\u96f7\u9526\u8f89", "faculty": "\u81ea\u52a8\u5316\u5b66\u9662"}, {"total": 19, "name": "\u6797\u534e\u9f99", "faculty": "\u81ea\u52a8\u5316\u5b66\u9662"}, {"total": 19, "name": "\u6797\u4f73\u9f50", "faculty": "\u81ea\u52a8\u5316\u5b66\u9662"}, {"total": 19, "name": "\u4e25\u6770\u5cf0", "faculty": "\u81ea\u52a8\u5316\u5b66\u9662"}, {"total": 19, "name": "\u5f20\u5149\u5bcc", "faculty": "\u81ea\u52a8\u5316\u5b66\u9662"}, {"total": 19, "name": "\u5f20\u6cfd\u660e", "faculty": "\u81ea\u52a8\u5316\u5b66\u9662"}], "total": 12220, "name": "\u81ea\u52a8\u5316\u5b66\u9662"}, {"students": [], "total": 7, "name": "\u73af\u5883\u79d1\u5b66\u4e0e\u5de5\u7a0b\u5b66\u9662"}, {"students": [], "total": 18, "name": "\u793e\u4f1a\u79d1\u5b66\u90e8"}, {"students": [], "total": 0, "name": "other"}, {"students": [{"total": 32, "name": "\u9648\u5bb9\u59b9", "faculty": "\u5916\u8bed\u7cfb"}, {"total": 22, "name": "\u6c5f\u6653\u4e91", "faculty": "\u5916\u8bed\u7cfb"}, {"total": 22, "name": "\u6797\u5efa\u5e73", "faculty": "\u5916\u8bed\u7cfb"}, {"total": 21, "name": "\u9ec4\u5e73", "faculty": "\u5916\u8bed\u7cfb"}, {"total": 20, "name": "\u674e\u7acb", "faculty": "\u5916\u8bed\u7cfb"}, {"total": 20, "name": "\u51af\u73ca\u73ca", "faculty": "\u5916\u8bed\u7cfb"}, {"total": 19, "name": "\u5510\u6b46", "faculty": "\u5916\u8bed\u7cfb"}, {"total": 19, "name": "\u9093\u6d01\u971e", "faculty": "\u5916\u8bed\u7cfb"}, {"total": 19, "name": "\u9ec4\u6c38\u8d5e", "faculty": "\u5916\u8bed\u7cfb"}, {"total": 19, "name": "\u6797\u6d01\u73ca", "faculty": "\u5916\u8bed\u7cfb"}, {"total": 19, "name": "\u9646\u7f8e\u7476", "faculty": "\u5916\u8bed\u7cfb"}, {"total": 19, "name": "\u5415\u6c38\u5a23", "faculty": "\u5916\u8bed\u7cfb"}, {"total": 19, "name": "\u8c22\u654f\u743c", "faculty": "\u5916\u8bed\u7cfb"}], "total": 5434, "name": "\u5916\u8bed\u7cfb"}, {"students": [], "total": 2, "name": "\u5916\u5355\u4f4d"}, {"students": [], "total": 31, "name": "\u7535\u6559\u4e2d\u5fc3"}, {"students": [], "total": 16, "name": "\u57fa\u5efa\u5904"}, {"students": [], "total": 14, "name": "\u4fdd\u536b\u5904\u3001\u6b66\u88c5\u90e8"}, {"students": [], "total": 2, "name": "\u534e\u5357\u519c\u4e1a\u5927\u5b66"}, {"students": [], "total": 3, "name": "\u534e\u5357\u5e08\u8303\u5927\u5b66"}, {"students": [{"total": 37, "name": "\u6881\u519b", "faculty": "\u6750\u6599\u80fd\u6e90\u5b66\u9662"}, {"total": 28, "name": "\u4e18\u7384\u6b66", "faculty": "\u6750\u6599\u80fd\u6e90\u5b66\u9662"}, {"total": 27, "name": "\u8c22\u66fe\u589e", "faculty": "\u6750\u6599\u80fd\u6e90\u5b66\u9662"}, {"total": 25, "name": "\u8c22\u56fd\u96c4", "faculty": "\u6750\u6599\u80fd\u6e90\u5b66\u9662"}, {"total": 24, "name": "\u97e6\u6ce2", "faculty": "\u6750\u6599\u80fd\u6e90\u5b66\u9662"}, {"total": 24, "name": "\u4ed8\u6b66\u65cb", "faculty": "\u6750\u6599\u80fd\u6e90\u5b66\u9662"}, {"total": 24, "name": "\u674e\u77f3\u680b", "faculty": "\u6750\u6599\u80fd\u6e90\u5b66\u9662"}, {"total": 21, "name": "\u5218\u667a\u806a", "faculty": "\u6750\u6599\u80fd\u6e90\u5b66\u9662"}, {"total": 21, "name": "\u4e25\u536b\u5b99", "faculty": "\u6750\u6599\u80fd\u6e90\u5b66\u9662"}, {"total": 20, "name": "\u5218\u5251", "faculty": "\u6750\u6599\u80fd\u6e90\u5b66\u9662"}, {"total": 20, "name": "\u6881\u96c4\u949f", "faculty": "\u6750\u6599\u80fd\u6e90\u5b66\u9662"}, {"total": 20, "name": "\u738b\u6ce2\u7fa4", "faculty": "\u6750\u6599\u80fd\u6e90\u5b66\u9662"}, {"total": 19, "name": "\u6797\u4e39", "faculty": "\u6750\u6599\u80fd\u6e90\u5b66\u9662"}], "total": 10593, "name": "\u6750\u6599\u80fd\u6e90\u5b66\u9662"}, {"students": [{"total": 29, "name": "\u8303\u6587\u5029", "faculty": "\u827a\u672f\u8bbe\u8ba1\u5b66\u9662"}, {"total": 27, "name": "\u5434\u5c0f\u6ee1", "faculty": "\u827a\u672f\u8bbe\u8ba1\u5b66\u9662"}, {"total": 27, "name": "\u5f20\u5fd7\u8c6a", "faculty": "\u827a\u672f\u8bbe\u8ba1\u5b66\u9662"}, {"total": 26, "name": "\u5f20\u4ed5\u6770", "faculty": "\u827a\u672f\u8bbe\u8ba1\u5b66\u9662"}, {"total": 25, "name": "\u5f20\u8212\u9759", "faculty": "\u827a\u672f\u8bbe\u8ba1\u5b66\u9662"}, {"total": 24, "name": "\u949f\u8363\u5bcc", "faculty": "\u827a\u672f\u8bbe\u8ba1\u5b66\u9662"}, {"total": 23, "name": "\u9ec4\u884d\u5a34", "faculty": "\u827a\u672f\u8bbe\u8ba1\u5b66\u9662"}, {"total": 23, "name": "\u90b1\u5e7f\u6cc9", "faculty": "\u827a\u672f\u8bbe\u8ba1\u5b66\u9662"}, {"total": 23, "name": "\u6e5b\u96ea\u5b9c", "faculty": "\u827a\u672f\u8bbe\u8ba1\u5b66\u9662"}, {"total": 22, "name": "\u8c22\u6c5d\u653f", "faculty": "\u827a\u672f\u8bbe\u8ba1\u5b66\u9662"}, {"total": 21, "name": "\u90ed\u4fcf\u5a25", "faculty": "\u827a\u672f\u8bbe\u8ba1\u5b66\u9662"}, {"total": 21, "name": "\u738b\u4e3d\u7f8e", "faculty": "\u827a\u672f\u8bbe\u8ba1\u5b66\u9662"}, {"total": 21, "name": "\u5f20\u65e5\u53cb", "faculty": "\u827a\u672f\u8bbe\u8ba1\u5b66\u9662"}, {"total": 21, "name": "\u90d1\u73e0\u7389", "faculty": "\u827a\u672f\u8bbe\u8ba1\u5b66\u9662"}, {"total": 20, "name": "\u6881\u7965\u575a", "faculty": "\u827a\u672f\u8bbe\u8ba1\u5b66\u9662"}, {"total": 20, "name": "\u6881\u8000\u5b97", "faculty": "\u827a\u672f\u8bbe\u8ba1\u5b66\u9662"}, {"total": 20, "name": "\u5218\u9526\u94f6", "faculty": "\u827a\u672f\u8bbe\u8ba1\u5b66\u9662"}, {"total": 20, "name": "\u8d75\u4f1f\u826f", "faculty": "\u827a\u672f\u8bbe\u8ba1\u5b66\u9662"}], "total": 7618, "name": "\u827a\u672f\u8bbe\u8ba1\u5b66\u9662"}, {"students": [], "total": 17, "name": "\u6821\u957f\u529e\u516c\u5ba4"}, {"students": [], "total": 40, "name": "\u9ad8\u6559\u7814\u7a76\u6240"}, {"students": [{"total": 35, "name": "\u674e\u6587\u4eae", "faculty": "\u673a\u7535\u5de5\u7a0b\u5b66\u9662"}, {"total": 30, "name": "\u9648\u5bb6\u9646", "faculty": "\u673a\u7535\u5de5\u7a0b\u5b66\u9662"}, {"total": 26, "name": "\u5c91\u5411\u534e", "faculty": "\u673a\u7535\u5de5\u7a0b\u5b66\u9662"}, {"total": 24, "name": "\u4f55\u5e7f\u6d9b", "faculty": "\u673a\u7535\u5de5\u7a0b\u5b66\u9662"}, {"total": 23, "name": "\u4faf\u6167\u6797", "faculty": "\u673a\u7535\u5de5\u7a0b\u5b66\u9662"}, {"total": 22, "name": "\u5e9e\u5218\u5e73", "faculty": "\u673a\u7535\u5de5\u7a0b\u5b66\u9662"}, {"total": 22, "name": "\u6731\u5e86\u6797", "faculty": "\u673a\u7535\u5de5\u7a0b\u5b66\u9662"}, {"total": 21, "name": "\u5434\u89c9", "faculty": "\u673a\u7535\u5de5\u7a0b\u5b66\u9662"}, {"total": 20, "name": "\u8c22\u6e05", "faculty": "\u673a\u7535\u5de5\u7a0b\u5b66\u9662"}, {"total": 20, "name": "\u65b9\u521b\u5764", "faculty": "\u673a\u7535\u5de5\u7a0b\u5b66\u9662"}, {"total": 20, "name": "\u9ece\u5c0f\u534e", "faculty": "\u673a\u7535\u5de5\u7a0b\u5b66\u9662"}, {"total": 20, "name": "\u738b\u79cb\u7389", "faculty": "\u673a\u7535\u5de5\u7a0b\u5b66\u9662"}, {"total": 19, "name": "\u9648\u7530", "faculty": "\u673a\u7535\u5de5\u7a0b\u5b66\u9662"}, {"total": 19, "name": "\u674e\u70fd", "faculty": "\u673a\u7535\u5de5\u7a0b\u5b66\u9662"}], "total": 54, "name": "\u673a\u7535\u5de5\u7a0b\u5b66\u9662"}, {"students": [{"total": 21, "name": "\u6e38\u68a6\u5170", "faculty": "\u56fe\u4e66\u9986"}, {"total": 20, "name": "\u8bb8\u4e3d\u73cd", "faculty": "\u56fe\u4e66\u9986"}, {"total": 19, "name": "\u4f55\u5e3c\u82f1", "faculty": "\u56fe\u4e66\u9986"}], "total": 282, "name": "\u56fe\u4e66\u9986"}, {"students": [], "total": 1, "name": "\u6c99\u6cb3\u6821\u533a\u529e"}, {"students": [{"total": 20, "name": "\u9ec4\u73ae\u6615", "faculty": "\u6587\u6cd5\u5b66\u9662"}, {"total": 20, "name": "\u674e\u4fcf\u71d5", "faculty": "\u6587\u6cd5\u5b66\u9662"}, {"total": 20, "name": "\u5f20\u6587\u82f1", "faculty": "\u6587\u6cd5\u5b66\u9662"}, {"total": 19, "name": "\u6e29\u60e0\u9759", "faculty": "\u6587\u6cd5\u5b66\u9662"}], "total": 2690, "name": "\u6587\u6cd5\u5b66\u9662"}, {"students": [], "total": 4, "name": "\u5b66\u62a5\u7f16\u8f91\u90e8"}, {"students": [], "total": 11, "name": "\u6821\u529e\u4ea7\u4e1a\u603b\u516c\u53f8"}, {"students": [], "total": 61, "name": "\u756a\u79ba\u5b66\u9662"}, {"students": [], "total": 15, "name": "\u6559\u52a1\u5904\u3001\u8bbe\u5907\u5904"}, {"students": [], "total": 12, "name": "\u7269\u7406\u4e0e\u5149\u7535\u5de5\u7a0b\u5b66\u9662"}, {"students": [{"total": 31, "name": "\u738b\u632f\u534e", "faculty": "\u8ba1\u7b97\u673a\u5b66\u9662"}, {"total": 27, "name": "\u6768\u7fa4\u751f", "faculty": "\u8ba1\u7b97\u673a\u5b66\u9662"}, {"total": 25, "name": "\u82cf\u4e50\u5e73", "faculty": "\u8ba1\u7b97\u673a\u5b66\u9662"}, {"total": 24, "name": "\u5f20\u6c38\u5065", "faculty": "\u8ba1\u7b97\u673a\u5b66\u9662"}, {"total": 22, "name": "\u8521\u6811\u654f", "faculty": "\u8ba1\u7b97\u673a\u5b66\u9662"}, {"total": 22, "name": "\u5e84\u4e9a\u6ce2", "faculty": "\u8ba1\u7b97\u673a\u5b66\u9662"}, {"total": 21, "name": "\u4ed8\u5b66\u6587", "faculty": "\u8ba1\u7b97\u673a\u5b66\u9662"}, {"total": 21, "name": "\u66fe\u695a\u5c55", "faculty": "\u8ba1\u7b97\u673a\u5b66\u9662"}, {"total": 20, "name": "\u53e4\u9669\u660e", "faculty": "\u8ba1\u7b97\u673a\u5b66\u9662"}, {"total": 20, "name": "\u6797\u590f\u541b", "faculty": "\u8ba1\u7b97\u673a\u5b66\u9662"}, {"total": 20, "name": "\u8499\u571f\u5174", "faculty": "\u8ba1\u7b97\u673a\u5b66\u9662"}, {"total": 20, "name": "\u90b1\u4e0a\u4fdd", "faculty": "\u8ba1\u7b97\u673a\u5b66\u9662"}, {"total": 20, "name": "\u6e29\u6d69\u5a01", "faculty": "\u8ba1\u7b97\u673a\u5b66\u9662"}, {"total": 20, "name": "\u8c22\u6811\u8d85", "faculty": "\u8ba1\u7b97\u673a\u5b66\u9662"}, {"total": 20, "name": "\u53f6\u5b97\u7403", "faculty": "\u8ba1\u7b97\u673a\u5b66\u9662"}, {"total": 20, "name": "\u5c91\u8fd0\u6cc9", "faculty": "\u8ba1\u7b97\u673a\u5b66\u9662"}, {"total": 19, "name": "\u5b59\u6960", "faculty": "\u8ba1\u7b97\u673a\u5b66\u9662"}, {"total": 19, "name": "\u738b\u6dfc", "faculty": "\u8ba1\u7b97\u673a\u5b66\u9662"}, {"total": 19, "name": "\u9648\u8363\u9526", "faculty": "\u8ba1\u7b97\u673a\u5b66\u9662"}, {"total": 19, "name": "\u9648\u601d\u8fdc", "faculty": "\u8ba1\u7b97\u673a\u5b66\u9662"}, {"total": 19, "name": "\u675c\u542f\u521a", "faculty": "\u8ba1\u7b97\u673a\u5b66\u9662"}, {"total": 19, "name": "\u9ec4\u4fca\u8c6a", "faculty": "\u8ba1\u7b97\u673a\u5b66\u9662"}, {"total": 19, "name": "\u9ec4\u6653\u5f6c", "faculty": "\u8ba1\u7b97\u673a\u5b66\u9662"}, {"total": 19, "name": "\u674e\u654f\u8f89", "faculty": "\u8ba1\u7b97\u673a\u5b66\u9662"}, {"total": 19, "name": "\u6797\u5c45\u6b63", "faculty": "\u8ba1\u7b97\u673a\u5b66\u9662"}, {"total": 19, "name": "\u6797\u6587\u6d9b", "faculty": "\u8ba1\u7b97\u673a\u5b66\u9662"}, {"total": 19, "name": "\u8096\u4eae\u53cb", "faculty": "\u8ba1\u7b97\u673a\u5b66\u9662"}, {"total": 19, "name": "\u859b\u6c38\u8425", "faculty": "\u8ba1\u7b97\u673a\u5b66\u9662"}, {"total": 19, "name": "\u90d1\u71d5\u94f6", "faculty": "\u8ba1\u7b97\u673a\u5b66\u9662"}], "total": 12075, "name": "\u8ba1\u7b97\u673a\u5b66\u9662"}, {"students": [], "total": 11, "name": "\u79d1\u6280\u5904"}, {"students": [], "total": 1, "name": "\u70ed\u80fd\u4e0e\u52a8\u529b\u5de5\u7a0b\u4e13\u4e1a"}, {"students": [], "total": 4, "name": "\u7f51\u7edc\u4e2d\u5fc3"}, {"students": [], "total": 4, "name": "\u827a\u672f\u8bbe\u8ba1\u4e13\u4e1a"}, {"students": [], "total": 24, "name": "\u6821\u533b\u9662"}, {"students": [{"total": 21, "name": "\u6881\u56fd\u6d2a", "faculty": "\u5e94\u7528\u6570\u5b66\u7cfb"}, {"total": 21, "name": "\u5218\u5fd7\u9756", "faculty": "\u5e94\u7528\u6570\u5b66\u7cfb"}, {"total": 20, "name": "\u9646\u4e30\u51ef", "faculty": "\u5e94\u7528\u6570\u5b66\u7cfb"}, {"total": 19, "name": "\u79e6\u8302\u884d", "faculty": "\u5e94\u7528\u6570\u5b66\u7cfb"}, {"total": 19, "name": "\u8bb8\u5c0f\u4f1f", "faculty": "\u5e94\u7528\u6570\u5b66\u7cfb"}], "total": 3648, "name": "\u5e94\u7528\u6570\u5b66\u7cfb"}, {"students": [], "total": 7, "name": "\u540e\u52e4\u670d\u52a1\u603b\u516c\u53f8"}, {"students": [], "total": 17, "name": "\u5de5\u7a0b\u4e0e\u8ba1\u7b97\u673a\u56fe\u5b66\u6559\u7814\u5ba4"}, {"students": [], "total": 2, "name": "\u8d22\u52a1\u5904\u3001\u56fd\u8d44\u529e"}]